jats/__init__.py
jats/converter.py
jats/main.py
jats/models.py
jats/parser.py
jats-0.1.0.dist-info/licenses/LICENSE
jats-0.1.0.dist-info/METADATA
jats-0.1.0.dist-info/WHEEL
jats-0.1.0.dist-info/entry_points.txt
jats-0.1.0.dist-info/top_level.txt
jats-0.1.0.dist-info/RECORD
