Metadata-Version: 2.4
Name: jats
Version: 0.1.0
Summary: JATS: Convert JATS XML articles to Markdown with peer review extraction
Author: A. Sina Booeshaghi
License-Expression: MIT
Keywords: jats,xml,markdown,converter,publishing,biorxiv,elife,peer-review
Classifier: Environment :: Console
Classifier: Intended Audience :: Science/Research
Classifier: Operating System :: OS Independent
Classifier: Programming Language :: Python :: 3.10
Classifier: Programming Language :: Python :: 3.11
Classifier: Programming Language :: Python :: 3.12
Classifier: Programming Language :: Python :: 3.13
Classifier: Topic :: Text Processing :: Markup :: XML
Classifier: Topic :: Utilities
Requires-Python: >=3.10
License-File: LICENSE
Requires-Dist: lxml>=5.0
Provides-Extra: dev
Requires-Dist: pytest>=8.0; extra == "dev"
Requires-Dist: pytest-cov>=6.0; extra == "dev"
Requires-Dist: ruff>=0.9; extra == "dev"
Dynamic: license-file
